{
  "project_info": {
    "project_number": "681968129120",
    "project_id": "classmate-b7d5d",
    "storage_bucket": "classmate-b7d5d.appspot.com"
  },
  "client": [
    {
      "client_info": {
        "mobilesdk_app_id": "1:681968129120:android:14f7b6ee688e5dc6515f05",
        "android_client_info": {
          "package_name": "com.example.timetable"
        }
      },
      "oauth_client": [],
      "api_key": [
        {
          "current_key": "AIzaSyB8uAB2ErB_G2uJHRpf9d28hhz8RQOd_54"
        }
      ],
      "services": {
        "appinvite_service": {
          "other_platform_oauth_client": []
        }
      }
    }
  ],
  "configuration_version": "1"
}